nltk_tools/__init__.py
nltk_tools/programs.py
nltk_tools-0.1.6.dist-info/licenses/LICENSE
nltk_tools-0.1.6.dist-info/METADATA
nltk_tools-0.1.6.dist-info/WHEEL
nltk_tools-0.1.6.dist-info/top_level.txt
nltk_tools-0.1.6.dist-info/RECORD
